

{ "comment": ["Positions of sensory cells, in [length, radius, angle]  (LRA) related to given neurons.",
              "Format: <neuron name>: ",
              "[distance from head normalized to 1, radius normalized to 1 (meaning cuticle position), angle with 0 pointing on z axis (right) and pi/2 y axis (top)]",
              "source: http://www.wormatlas.org/neuronalwiring.html#Neuronconnections",
              "file: http://www.wormatlas.org/images/NeuronFixedPoints.xls"],              
 "sensoryPosJSON": {
   "constants":{
       "angleL":90.0,  "angleD":180.0,  "angleR":270.0,  "angleV":0.0,
       "angleDL":120.0, "angleDR":240.0, "angleVR":300.0, "angleVL":60.0,
       "amphDist":0.0,      "amphRad":0.8,
       "ilDist":0.0,        "ilRad":0.6,
       "olDist":0.01,       "olRad":0.9,       
       "cephDist":0.01,     "cephRad":0.9,
       "amphWingDist":0.01, "amphWingRad":0.8,
       "antDeirDist":0.13,  "antDeirRad":1,
       "postDeirDist":0.68, "postDeirRad":1,
       "phasmDist":0.95,    "phasmRad":1,
       "unknownDist":0,     "unknownRad":0.6             
   },
   "positions":{
        "ADFL   ": ["amphDist", "amphRad", "angleL"],
        "ADFR   ": ["amphDist", "amphRad", "angleR"],
        "ADLL   ": ["amphDist", "amphRad", "angleL"],
        "ADLR   ": ["amphDist", "amphRad", "angleR"],
        "AFDL   ": ["amphDist", "amphRad", "angleL"],
        "AFDR   ": ["amphDist", "amphRad", "angleR"],
        "ASEL   ": ["amphDist", "amphRad", "angleL"],
        "ASER   ": ["amphDist", "amphRad", "angleR"],
        "ASGL   ": ["amphDist", "amphRad", "angleL"],
        "ASGR   ": ["amphDist", "amphRad", "angleR"],
        "ASHL   ": ["amphDist", "amphRad", "angleL"],
        "ASHR   ": ["amphDist", "amphRad", "angleR"],
        "ASIL   ": ["amphDist", "amphRad", "angleL"],
        "ASIR   ": ["amphDist", "amphRad", "angleR"],
        "ASJL   ": ["amphDist", "amphRad", "angleL"],
        "ASJR   ": ["amphDist", "amphRad", "angleR"],
        "ASKL   ": ["amphDist", "amphRad", "angleL"],
        "ASKR   ": ["amphDist", "amphRad", "angleR"],
        
        "AWAL   ": ["amphWingDist", "amphRad", "angleL"],
        "AWAR   ": ["amphWingDist", "amphRad", "angleR"],
        "AWBL   ": ["amphWingDist", "amphRad", "angleL"],
        "AWBR   ": ["amphWingDist", "amphRad", "angleR"],
        "AWCL   ": ["amphWingDist", "amphRad", "angleL"],
        "AWCR   ": ["amphWingDist", "amphRad", "angleR"],
        "IL2L   ": ["ilDist", "ilRad",  "angleL"],
        "IL2R   ": ["ilDist", "ilRad",  "angleR"],
        "IL2VL  ": ["ilDist", "ilRad", "angleVL"],
        "IL2VR  ": ["ilDist", "ilRad", "angleVR"],
        "IL2DL  ": ["ilDist", "ilRad", "angleDL"],
        "IL2DR  ": ["ilDist", "ilRad", "angleDR"],
        "PHAL   ": ["phasmDist", "phasmRad", "angleL"],
        "PHAR   ": ["phasmDist", "phasmRad", "angleR"],
        "PHBL   ": ["phasmDist", "phasmRad", "angleL"],
        "PHBR   ": ["phasmDist", "phasmRad", "angleR"],
        
        "AQR    ": [0.14, 0.5,  "angleR"],
        "PQR    ": [0.95, 0.5,  "angleL"],
        "URXL   ": ["ilDist", "ilRad",  "angleDL"],
        "URXR   ": ["ilDist", "ilRad",  "angleDR"],
        "BAGL   ": ["ilDist", "ilRad",   "angleL"],
        "BAGR   ": ["ilDist", "ilRad",   "angleR"],
        
      
        "AUAL   ": ["amphDist", "amphRad", "angleL"],
        "AUAR   ": ["amphDist", "amphRad", "angleR"],
        "URYDL  ": ["olDist", "olRad",  "angleDL"],
        "URYDR  ": ["olDist", "olRad",  "angleDR"],
        "URYVL  ": ["olDist", "olRad",  "angleVL"],
        "URYVR  ": ["olDist", "olRad",  "angleVR"],
        "URADL  ": ["olDist", "olRad",  "angleDL"],
        "URADR  ": ["olDist", "olRad",  "angleDR"],
        "URAVL  ": ["olDist", "olRad",  "angleVL"],
        "URAVR  ": ["olDist", "olRad",  "angleVR"],
        "URBL   ": ["unknownDist", "unknownRad",  "angleL"],
        "URBR   ": ["unknownDist", "unknownRad",  "angleR"],
        
        "FLPL   ": ["ilDist", "ilRad",  "angleL"],
        "FLPR   ": ["ilDist", "ilRad",  "angleR"],
        "PVDL   ": [0.65, 1.0,  "angleL"],
        "PVDR   ": [0.65, 1.0,  "angleR"],
        "PHCL   ": [1.00, 1.0,  "angleL"],
        "PHCR   ": [1.00, 1.0,  "angleR"],

        "IL1L   ": ["ilDist", "ilRad",  "angleL"],
        "IL1R   ": ["ilDist", "ilRad",  "angleR"],
        "IL1VL  ": ["ilDist", "ilRad", "angleVL"],
        "IL1VR  ": ["ilDist", "ilRad", "angleVR"],
        "IL1DL  ": ["ilDist", "ilRad", "angleDL"],
        "IL1DR  ": ["ilDist", "ilRad", "angleDR"],      
        "CEPDL  ": ["cephDist", "cephRad", "angleDL"],
        "CEPDR  ": ["cephDist", "cephRad", "angleDR"],
        "CEPVL  ": ["cephDist", "cephRad", "angleVL"],
        "CEPVR  ": ["cephDist", "cephRad", "angleVR"],
        "OLLL   ": ["olDist", "olRad",  "angleL"],
        "OLLR   ": ["olDist", "olRad",  "angleR"],
        "OLQDL  ": ["olDist", "olRad", "angleDL"],
        "OLQDR  ": ["olDist", "olRad", "angleDR"],
        "OLQVL  ": ["olDist", "olRad", "angleVL"],
        "OLQVR  ": ["olDist", "olRad", "angleVR"],
        "ADEL   ": ["antDeirDist" , "antDeirRad" , "angleL"],
        "ADER   ": ["antDeirDist" , "antDeirRad" , "angleR"],
        "PDEL   ": ["postDeirDist", "postDeirRad", "angleL"],
        "PDER   ": ["postDeirDist", "postDeirRad", "angleR"]       
   },
   "positions_PE_NotConsidered":{
        "ALNL   ": [1, 1, "angleL"],      
        "ALNR   ": [1, 1, "angleR"],
        "PLNL   ": [1, 1, "angleL"],
        "PLNR   ": [1, 1, "angleR"],
        "SDQL   ": [0.7, 1, "angleDL"],
        "SDQR   ": [0.4, 1, "angleDR"],
        "BDUL   ": [0.3, 1,  "angleL"],
        "BDUR   ": [0.3, 1,  "angleR"],
        
        "AVM    ": [0,19, 1, "angleV"],
        "ALML   ": [0,25, 1, "angleL"],
        "ALMR   ": [0,25, 1, "angleR"],
        "PVM    ": [0,47, 1, "angleV"],
        "PLML   ": [0,71, 1, "angleL"],
        "PLMR   ": [0,71, 1, "angleR"],
               
        "PVR    ": [1.0, 1, "angleV"],
        "AVG    ": [0.2, 1, "angleV"]
   }

 }}
 
